ros_rosidl_typesupport_introspection_c-4.9.5.data/data/include/rosidl_typesupport_introspection_c/rosidl_typesupport_introspection_c/field_types.h
ros_rosidl_typesupport_introspection_c-4.9.5.data/data/include/rosidl_typesupport_introspection_c/rosidl_typesupport_introspection_c/identifier.h
ros_rosidl_typesupport_introspection_c-4.9.5.data/data/include/rosidl_typesupport_introspection_c/rosidl_typesupport_introspection_c/message_introspection.h
ros_rosidl_typesupport_introspection_c-4.9.5.data/data/include/rosidl_typesupport_introspection_c/rosidl_typesupport_introspection_c/service_introspection.h
ros_rosidl_typesupport_introspection_c-4.9.5.data/data/include/rosidl_typesupport_introspection_c/rosidl_typesupport_introspection_c/visibility_control.h
ros_rosidl_typesupport_introspection_c-4.9.5.data/data/lib/librosidl_typesupport_introspection_c.so
ros_rosidl_typesupport_introspection_c-4.9.5.data/data/lib/python3.13/site-packages/rosidl_typesupport_introspection_c/__init__.py
ros_rosidl_typesupport_introspection_c-4.9.5.data/data/lib/python3.13/site-packages/rosidl_typesupport_introspection_c/cli.py
ros_rosidl_typesupport_introspection_c-4.9.5.data/data/lib/python3.13/site-packages/rosidl_typesupport_introspection_c/__pycache__/__init__.cpython-313.pyc
ros_rosidl_typesupport_introspection_c-4.9.5.data/data/lib/python3.13/site-packages/rosidl_typesupport_introspection_c/__pycache__/cli.cpython-313.pyc
ros_rosidl_typesupport_introspection_c-4.9.5.data/data/lib/python3.13/site-packages/rosidl_typesupport_introspection_c-4.9.5-py3.13.egg-info/PKG-INFO
ros_rosidl_typesupport_introspection_c-4.9.5.data/data/lib/python3.13/site-packages/rosidl_typesupport_introspection_c-4.9.5-py3.13.egg-info/SOURCES.txt
ros_rosidl_typesupport_introspection_c-4.9.5.data/data/lib/python3.13/site-packages/rosidl_typesupport_introspection_c-4.9.5-py3.13.egg-info/dependency_links.txt
ros_rosidl_typesupport_introspection_c-4.9.5.data/data/lib/python3.13/site-packages/rosidl_typesupport_introspection_c-4.9.5-py3.13.egg-info/entry_points.txt
ros_rosidl_typesupport_introspection_c-4.9.5.data/data/lib/python3.13/site-packages/rosidl_typesupport_introspection_c-4.9.5-py3.13.egg-info/top_level.txt
ros_rosidl_typesupport_introspection_c-4.9.5.data/data/lib/rosidl_typesupport_introspection_c/rosidl_typesupport_introspection_c
ros_rosidl_typesupport_introspection_c-4.9.5.data/data/share/ament_index/resource_index/package_run_dependencies/rosidl_typesupport_introspection_c
ros_rosidl_typesupport_introspection_c-4.9.5.data/data/share/ament_index/resource_index/packages/rosidl_typesupport_introspection_c
ros_rosidl_typesupport_introspection_c-4.9.5.data/data/share/ament_index/resource_index/parent_prefix_path/rosidl_typesupport_introspection_c
ros_rosidl_typesupport_introspection_c-4.9.5.dist-info/METADATA
ros_rosidl_typesupport_introspection_c-4.9.5.dist-info/WHEEL
ros_rosidl_typesupport_introspection_c-4.9.5.dist-info/entry_points.txt
ros_rosidl_typesupport_introspection_c-4.9.5.dist-info/top_level.txt
ros_rosidl_typesupport_introspection_c-4.9.5.dist-info/RECORD
