Metadata-Version: 2.4
Name: ros-rosidl-typesupport-introspection-c
Version: 4.9.5
Summary: A ROS package for C typesupport introspection, enabling dynamic message access and manipulation.
Requires-Dist: ros-rosidl-cmake~=4.9.5
Requires-Dist: ros-ament-index-python~=1.11.0
Requires-Dist: ros-rosidl-pycommon~=4.9.5
Requires-Dist: ros-rosidl-runtime-c~=4.9.5
Requires-Dist: ros-rosidl-typesupport-interface~=4.9.5
Requires-Dist: ros-rosidl-generator-c~=4.9.5
Requires-Dist: ros-rosidl-cli~=4.9.5
Requires-Dist: ros-rosidl-parser~=4.9.5
Dynamic: description
Dynamic: description-content-type
Dynamic: requires-dist
Dynamic: summary
